putplace_assist/__init__.py
putplace_assist/__main__.py
putplace_assist/activity.py
putplace_assist/cli.py
putplace_assist/config.py
putplace_assist/configure.py
putplace_assist/daemon.py
putplace_assist/database.py
putplace_assist/main.py
putplace_assist/models.py
putplace_assist/ppclient.py
putplace_assist/scanner.py
putplace_assist/sha256_processor.py
putplace_assist/uploader.py
putplace_assist/uploader_v3.py
putplace_assist/version.py
putplace_assist/watcher.py
putplace_assist/scripts/__init__.py
putplace_assist/scripts/pp_assist_purge.py
putplace_assist/static/index.html
putplace_assist/static/images/favicon.svg
putplace_assist-0.2.2.dist-info/METADATA
putplace_assist-0.2.2.dist-info/WHEEL
putplace_assist-0.2.2.dist-info/entry_points.txt
putplace_assist-0.2.2.dist-info/RECORD
