Metadata-Version: 2.4
Name: putplace-assist
Version: 0.2.2
Summary: Local assistant daemon for PutPlace file uploads (includes pp_client CLI)
Author-email: Joe Drumgoole <joe@joedrumgoole.com>
License: Apache-2.0
Keywords: daemon,file,metadata,putplace,upload
Classifier: Development Status :: 3 - Alpha
Classifier: Intended Audience :: Developers
Classifier: License :: OSI Approved :: Apache Software License
Classifier: Programming Language :: Python :: 3
Classifier: Programming Language :: Python :: 3.10
Classifier: Programming Language :: Python :: 3.11
Classifier: Programming Language :: Python :: 3.12
Requires-Python: >=3.10
Requires-Dist: aiosqlite>=0.19.0
Requires-Dist: cryptography>=41.0.0
Requires-Dist: fastapi>=0.110.0
Requires-Dist: httpx>=0.26.0
Requires-Dist: pydantic-settings>=2.1.0
Requires-Dist: pydantic>=2.6.0
Requires-Dist: python-dotenv>=1.0.0
Requires-Dist: rich>=13.7.0
Requires-Dist: sse-starlette>=1.6.0
Requires-Dist: tomli-w>=1.0.0
Requires-Dist: tomli>=2.0.0; python_version < '3.11'
Requires-Dist: uvicorn[standard]>=0.27.0
Requires-Dist: watchdog>=3.0.0
Provides-Extra: dev
Requires-Dist: httpx>=0.26.0; extra == 'dev'
Requires-Dist: pytest-asyncio>=0.23.0; extra == 'dev'
Requires-Dist: pytest-cov>=4.1.0; extra == 'dev'
Requires-Dist: pytest>=8.0.0; extra == 'dev'
Requires-Dist: ruff>=0.3.0; extra == 'dev'
